windmillcomputev1/__init__.py
windmillcomputev1/client/__init__.py
windmillcomputev1/client/compute_api_compute.py
windmillcomputev1/client/compute_api_filesystem.py
windmillcomputev1/client/compute_client.py
windmillcomputev1/filesystem/__init__.py
windmillcomputev1/filesystem/blobstore.py
windmillcomputev1/filesystem/local.py
windmillcomputev1/filesystem/s3.py
windmillcomputev1/tools/__init__.py
windmillcomputev1/tools/download_kubeconfig.py
windmillcomputev1/tools/s3_clean_tool.py
windmillcomputev1/tools/upload.py
windmill_compute-1.0.0.36.dist-info/METADATA
windmill_compute-1.0.0.36.dist-info/WHEEL
windmill_compute-1.0.0.36.dist-info/top_level.txt
windmill_compute-1.0.0.36.dist-info/RECORD
