Metadata-Version: 2.1
Name: windmill-compute
Version: 1.0.0.36
Summary: sdk in python for windmill compute
Home-page: http://www.ai.com
Author: yangtingyu01
License: MIT
Classifier: Programming Language :: Python
Classifier: Programming Language :: Python :: 3
Classifier: Programming Language :: Python :: 3.7
Classifier: Programming Language :: Python :: 3.8
Classifier: Programming Language :: Python :: 3.9
Requires-Python: >=3.6
Requires-Dist: bce-python-sdk (==0.8.87)
Requires-Dist: boto3 (<=1.35.98)
Requires-Dist: pandas (==2.0.3)
Requires-Dist: s3fs (==0.4.2)
Requires-Dist: pyarrow
Requires-Dist: bce-internal-sdk
Requires-Dist: bcelogger
Requires-Dist: dateparser
